{
  "_class": "text",
  "attributedString": {
    "_class": "attributedString",
    "attributes": [
      {
        "_class": "stringAttribute",
        "attributes": {
          "MSAttributedStringColorAttribute": {
            "_class": "color",
            "alpha": 1,
            "blue": 0,
            "green": 0,
            "red": 0
          },
          "MSAttributedStringFontAttribute": {
            "_class": "fontDescriptor",
            "attributes": {
              "name": "OpenSans-Semibold",
              "size": 16
            }
          },
          "kerning": 0,
          "paragraphStyle": {
            "_class": "paragraphStyle",
            "lineHeightMultiple": 1,
            "maximumLineHeight": 30,
            "minimumLineHeight": 30
          },
          "strikethroughStyle": 0,
          "underlineStyle": 0
        },
        "length": 188,
        "location": 0
      }
    ],
    "string": "Mobile: Well here's some inspirational quotes for you: “Good design is making something intelligible and memorable. Great design is making something memorable and meaningful”: Dieter Rams."
  },
  "automaticallyDrawOnUnderlyingPath": false,
  "booleanOperation": 0,
  "clippingMaskMode": 0,
  "do_objectID": "DDD8DB1A-7201-4B38-995F-78F7BE1AC001",
  "dontSynchroniseWithSymbol": false,
  "exportOptions": {
    "_class": "exportOptions",
    "do_objectID": "D144AE8B-4BED-40F3-A8A6-412CF484D645",
    "exportFormats": [
    ],
    "includedLayerIds": [
    ],
    "layerOptions": 0,
    "shouldTrim": false
  },
  "frame": {
    "_class": "rect",
    "constrainProportions": false,
    "do_objectID": "77EDD219-7B94-46A7-AA8C-DF228C9B62DC",
    "height": 180,
    "width": 320,
    "x": -160,
    "y": 675
  },
  "glyphBounds": "{{0, 0}, {0, 0}}",
  "hasClippingMask": false,
  "isFixedToViewport": false,
  "isFlippedHorizontal": false,
  "isFlippedVertical": false,
  "isLocked": false,
  "isVisible": true,
  "layerListExpandedType": 0,
  "lineSpacingBehaviour": 2,
  "name": "Mobile: Well here's some inspirational quotes for you: “Good design is making something intelligible and memorable. Great design is making something memorable and meaningful”: Dieter Rams.",
  "nameIsFixed": false,
  "resizingConstraint": 63,
  "resizingType": 0,
  "rotation": 0,
  "shouldBreakMaskChain": false,
  "style": {
    "_class": "style",
    "do_objectID": "AD1449F5-C24F-4299-981E-6B55B33332BC",
    "endMarkerType": 0,
    "miterLimit": 10,
    "startMarkerType": 0,
    "windingRule": 1
  },
  "textBehaviour": 1
}